mongodoc
