Metadata-Version: 1.0
Name: mongodoc
Version: 0.3.2
Summary: Creates a uml-like diagram for a nested mongodb document
Home-page: https://github.com/cswank/mongodoc
Author: Craig Swank
Author-email: craigswank@gmail.com
License: MIT License
Keywords: mongodb database schema documentation
Platform: UNKNOWN
